LICENSE
MANIFEST.in
README.rst
setup.cfg
setup.py
releasetasks/__init__.py
releasetasks/util.py
releasetasks.egg-info/PKG-INFO
releasetasks.egg-info/SOURCES.txt
releasetasks.egg-info/dependency_links.txt
releasetasks.egg-info/not-zip-safe
releasetasks.egg-info/requires.txt
releasetasks.egg-info/top_level.txt
releasetasks/templates/firefox/bb_update_verify.yml.tmpl
releasetasks/templates/firefox/bouncer.yml.tmpl
releasetasks/templates/firefox/bouncer_aliases.yml.tmpl
releasetasks/templates/firefox/checksums.yml.tmpl
releasetasks/templates/firefox/common_extras.yml.tmpl
releasetasks/templates/firefox/enUS.yml.tmpl
releasetasks/templates/firefox/final_verify.yml.tmpl
releasetasks/templates/firefox/l10n.yml.tmpl
releasetasks/templates/firefox/l10n_changesets.yml.tmpl
releasetasks/templates/firefox/partner_repacks.yml.tmpl
releasetasks/templates/firefox/post_release_human_decision.yml.tmpl
releasetasks/templates/firefox/push_to_releases.yml.tmpl
releasetasks/templates/firefox/release_graph.yml.tmpl
releasetasks/templates/firefox/source.yml.tmpl
releasetasks/templates/firefox/tc_update_verify.yml.tmpl
releasetasks/templates/firefox/updates.yml.tmpl
releasetasks/templates/firefox/uptake_monitoring.yml.tmpl
releasetasks/templates/firefox/version_bump.yml.tmpl