Metadata-Version: 1.1
Name: releasetasks
Version: 0.4.0
Summary: Mozilla Release Promotion Tasks contains code to generate
Home-page: https://github.com/rail/releasetasks
Author: Rail Aliiev
Author-email: rail@mozilla.com
License: MPL
Keywords: releasetasks
Platform: UNKNOWN
Classifier: Development Status :: 2 - Pre-Alpha
Classifier: Intended Audience :: Developers
Classifier: License :: OSI Approved :: BSD License
Classifier: Natural Language :: English
Classifier: Programming Language :: Python :: 2.7
